[
  {
    "code": "RD1.13",
    "subject": "Radiodiagnosis",
    "phase": "Phase-3A",
    "description": "",
    "type": "K",
    "level": "Must Know",
    "domain": "Cognitive",
    "core": true,
    "integration": []
  },
  {
    "code": "RD1.13",
    "subject": "Radiodiagnosis",
    "phase": "Phase-3A",
    "description": "",
    "type": "K",
    "level": "Must Know",
    "domain": "Cognitive",
    "core": true,
    "integration": []
  },
  {
    "code": "RD1.1",
    "subject": "Radiodiagnosis",
    "phase": "Phase-3A",
    "description": "",
    "type": "K",
    "level": "Must Know",
    "domain": "Cognitive",
    "core": true,
    "integration": []
  },
  {
    "code": "RD1.2",
    "subject": "Radiodiagnosis",
    "phase": "Phase-3A",
    "description": "",
    "type": "K",
    "level": "Must Know",
    "domain": "Cognitive",
    "core": true,
    "integration": []
  },
  {
    "code": "RD1.3",
    "subject": "Radiodiagnosis",
    "phase": "Phase-3A",
    "description": "",
    "type": "K",
    "level": "Must Know",
    "domain": "Cognitive",
    "core": true,
    "integration": []
  },
  {
    "code": "RD1.4",
    "subject": "Radiodiagnosis",
    "phase": "Phase-3A",
    "description": "",
    "type": "K",
    "level": "Must Know",
    "domain": "Cognitive",
    "core": true,
    "integration": []
  },
  {
    "code": "RD1.5",
    "subject": "Radiodiagnosis",
    "phase": "Phase-3A",
    "description": "",
    "type": "K",
    "level": "Must Know",
    "domain": "Cognitive",
    "core": true,
    "integration": []
  },
  {
    "code": "RD1.6",
    "subject": "Radiodiagnosis",
    "phase": "Phase-3A",
    "description": "",
    "type": "K",
    "level": "Must Know",
    "domain": "Cognitive",
    "core": true,
    "integration": []
  },
  {
    "code": "RD1.7",
    "subject": "Radiodiagnosis",
    "phase": "Phase-3A",
    "description": "",
    "type": "K",
    "level": "Must Know",
    "domain": "Cognitive",
    "core": true,
    "integration": []
  },
  {
    "code": "RD1.8",
    "subject": "Radiodiagnosis",
    "phase": "Phase-3A",
    "description": "",
    "type": "K",
    "level": "Must Know",
    "domain": "Cognitive",
    "core": true,
    "integration": []
  },
  {
    "code": "RD1.9",
    "subject": "Radiodiagnosis",
    "phase": "Phase-3A",
    "description": "",
    "type": "K",
    "level": "Must Know",
    "domain": "Cognitive",
    "core": true,
    "integration": []
  },
  {
    "code": "RD1.10",
    "subject": "Radiodiagnosis",
    "phase": "Phase-3A",
    "description": "",
    "type": "K",
    "level": "Must Know",
    "domain": "Cognitive",
    "core": true,
    "integration": []
  },
  {
    "code": "RD1.11",
    "subject": "Radiodiagnosis",
    "phase": "Phase-3A",
    "description": "",
    "type": "K",
    "level": "Must Know",
    "domain": "Cognitive",
    "core": true,
    "integration": []
  },
  {
    "code": "RD1.12",
    "subject": "Radiodiagnosis",
    "phase": "Phase-3A",
    "description": "",
    "type": "K",
    "level": "Must Know",
    "domain": "Cognitive",
    "core": true,
    "integration": []
  },
  {
    "code": "RD1.13",
    "subject": "Radiodiagnosis",
    "phase": "Phase-3A",
    "description": "",
    "type": "K",
    "level": "Must Know",
    "domain": "Cognitive",
    "core": true,
    "integration": []
  }
]